is_matrix_forge/__init__.py
is_matrix_forge/assets/__init__.py
is_matrix_forge/assets/audio/__init__.py
is_matrix_forge/assets/audio/files/__init__.py
is_matrix_forge/assets/audio/files/plugged.wav
is_matrix_forge/assets/audio/files/unplugged.wav
is_matrix_forge/assets/char_map.json
is_matrix_forge/assets/digit_map.py
is_matrix_forge/assets/font_map/__init__.py
is_matrix_forge/assets/font_map/base.py
is_matrix_forge/assets/font_map/builders.py
is_matrix_forge/assets/font_map/helpers.py
is_matrix_forge/assets/font_map/models/__init__.py
is_matrix_forge/assets/font_map/models/glyph.py
is_matrix_forge/common/__init__.py
is_matrix_forge/common/decorators/__init__.py
is_matrix_forge/common/decorators/freeze_setter.py
is_matrix_forge/common/dirs.py
is_matrix_forge/common/helpers/__init__.py
is_matrix_forge/common/helpers/errors.py
is_matrix_forge/common/helpers/github_api.py
is_matrix_forge/common/logging/__init__.py
is_matrix_forge/common/logging/log_exceptions.py
is_matrix_forge/designer_gui/__init__.py
is_matrix_forge/designer_gui/main_window/__init__.py
is_matrix_forge/designer_gui/main_window/layout/__init__.py
is_matrix_forge/designer_gui/main_window/layout/button_grid/__init__.py
is_matrix_forge/designer_gui/main_window/layout/button_grid/column.py
is_matrix_forge/designer_gui/main_window/layout/button_grid/grid.py
is_matrix_forge/designer_gui/main_window/layout/menu_bar.py
is_matrix_forge/designer_gui/main_window/streamlit_app.py
is_matrix_forge/dev_tools/__init__.py
is_matrix_forge/dev_tools/debug.py
is_matrix_forge/dev_tools/presets.py
is_matrix_forge/inputmodule/__init__.py
is_matrix_forge/inputmodule/b1display.py
is_matrix_forge/inputmodule/c1minimal.py
is_matrix_forge/inputmodule/font.py
is_matrix_forge/inputmodule/helpers/__init__.py
is_matrix_forge/inputmodule/ledmatrix.py
is_matrix_forge/led_matrix/__init__.py
is_matrix_forge/led_matrix/commands/__init__.py
is_matrix_forge/led_matrix/commands/map.py
is_matrix_forge/led_matrix/constants.py
is_matrix_forge-1.0.0.dev27.dist-info/entry_points.txt
is_matrix_forge-1.0.0.dev27.dist-info/LICENSE.md
is_matrix_forge-1.0.0.dev27.dist-info/METADATA
is_matrix_forge-1.0.0.dev27.dist-info/WHEEL
is_matrix_forge-1.0.0.dev27.dist-info/RECORD
