Metadata-Version: 2.3
Name: IS-Matrix-Forge
Version: 1.0.0.dev27
Summary: 
License: MIT
Keywords: led,matrix,framework,hardware
Author: Taylor B.
Author-email: t.blackstone@inspyre.tech
Requires-Python: >=3.12,<4.0
Classifier: License :: OSI Approved :: MIT License
Classifier: Programming Language :: Python :: 3
Classifier: Programming Language :: Python :: 3.12
Classifier: Programming Language :: Python :: 3.13
Provides-Extra: clipboard-support
Requires-Dist: aliaser (>=1.0.0.dev4,<2.0.0)
Requires-Dist: chime (>=0.7.0,<0.8.0)
Requires-Dist: clipboard (>=0.0.4,<0.0.5) ; extra == "clipboard-support"
Requires-Dist: easy-exit-calls (>=1.0.0.dev1,<2.0.0)
Requires-Dist: imapclient (==3.0.1)
Requires-Dist: inspy-logger (>=3.2.3,<4.0.0)
Requires-Dist: inspyre-toolbox (>=1.6.0.dev23)
Requires-Dist: ipywidgets (==8.1.7)
Requires-Dist: notebook (>=7.4.4,<8.0.0)
Requires-Dist: opencv-python (>=4.11.0.86,<5.0.0.0)
Requires-Dist: pillow (>=11.2.1,<12.0.0)
Requires-Dist: psutil (==6.1.1)
Requires-Dist: pyserial (>=3.5,<4.0)
Requires-Dist: pysimplegui-4-foss (==4.60.4.1)
Requires-Dist: pysimpleguiweb (==0.39.0)
Requires-Dist: requests (>=2.32.4,<3.0.0)
Requires-Dist: wmi (>=1.5.1,<2.0.0) ; sys_platform == "win32"
Project-URL: Homepage, https://github.com/Inspyre-Softworks/IS-Matrix-Forge
Project-URL: Repository, https://github.com/Inspyre-Softworks/IS-Matrix-Forge
